Metadata-Version: 2.1
Name: AEEGGOOSS
Version: 0.2
Summary: Gamaa
Author: AegosCOOOD
Classifier: Programming Language :: Python :: 3
Classifier: Operating System :: OS Independent
Classifier: License :: OSI Approved :: MIT License
License-File: LICENSE.txt
